LICENSE.txt
MANIFEST.in
README.txt
setup.py
pyramid_fas_openid/__init__.py
pyramid_fas_openid/view.py
pyramid_fas_openid.egg-info/PKG-INFO
pyramid_fas_openid.egg-info/SOURCES.txt
pyramid_fas_openid.egg-info/dependency_links.txt
pyramid_fas_openid.egg-info/requires.txt
pyramid_fas_openid.egg-info/top_level.txt