Metadata-Version: 1.1
Name: pyramid-fas-openid
Version: 0.3.9
Summary: A view for pyramid that functions as an OpenID consumer.
Home-page: http://github.com/lmacken/pyramid_fas_openid
Author: Luke Macken, Thomas Hill
Author-email: lmacken@redhat.com
License: BSD-derived (http://www.repoze.org/LICENSE.txt)
Keywords: pyramid openid fedora
Platform: UNKNOWN
Classifier: Intended Audience :: Developers
Classifier: License :: Repoze Public License
Classifier: Programming Language :: Python
Classifier: Programming Language :: Python :: 2.7
Classifier: Programming Language :: Python :: 3.6
Classifier: Framework :: Pyramid
Classifier: Topic :: Internet :: WWW/HTTP
Classifier: Topic :: Internet :: WWW/HTTP :: WSGI
